setup.py
gerrit_check.egg-info/PKG-INFO
gerrit_check.egg-info/SOURCES.txt
gerrit_check.egg-info/dependency_links.txt
gerrit_check.egg-info/entry_points.txt
gerrit_check.egg-info/requires.txt
gerrit_check.egg-info/top_level.txt
gerritcheck/__init__.py
gerritcheck/check.py