Metadata-Version: 1.0
Name: gerrit-check
Version: 0.1.1
Summary: Line annotations for syntax checkers for Gerrit
Home-page: https://github.com/grundprinzip/gerrit-check
Author: Martin Grund
Author-email: grundprinzip@gmail.com
License: Apache 2.0
Platform: Linux
